LICENSE
MANIFEST.in
README.md
README.pypi
pyproject.toml
requirements.txt
setup.py
Orange3_signal.egg-info/PKG-INFO
Orange3_signal.egg-info/SOURCES.txt
Orange3_signal.egg-info/dependency_links.txt
Orange3_signal.egg-info/entry_points.txt
Orange3_signal.egg-info/namespace_packages.txt
Orange3_signal.egg-info/not-zip-safe
Orange3_signal.egg-info/requires.txt
Orange3_signal.egg-info/top_level.txt
orangecontrib/__init__.py
orangecontrib/signal/__init__.py
orangecontrib/signal/widgets/__init__.py
orangecontrib/signal/widgets/owunwrap.py
orangecontrib/signal/widgets/icons/category.svg
orangecontrib/signal/widgets/icons/unwrap.svg